starcatalogquery/__init__.py
starcatalogquery/astrometry_corrections.py
starcatalogquery/catalog_check.py
starcatalogquery/catalog_download.py
starcatalogquery/catalog_index.py
starcatalogquery/catalog_query.py
starcatalogquery/classes.py
starcatalogquery/invariantfeatures.py
starcatalogquery/tiles_draw.py
starcatalogquery/wcs.py
starcatalogquery/utils/Const.py
starcatalogquery/utils/__init__.py
starcatalogquery/utils/data_download.py
starcatalogquery/utils/data_prepare.py
starcatalogquery/utils/df2info.py
starcatalogquery/utils/math.py
starcatalogquery/utils/starcatalog_statistic.py
starcatalogquery/utils/try_download.py
starcatalogquery-2.0.1.dist-info/licenses/LICENSE
starcatalogquery-2.0.1.dist-info/METADATA
starcatalogquery-2.0.1.dist-info/WHEEL
starcatalogquery-2.0.1.dist-info/top_level.txt
starcatalogquery-2.0.1.dist-info/RECORD
