Metadata-Version: 2.4
Name: starcatalogquery
Version: 2.0.1
Summary: A package for building an offline star catalog query database
Home-page: https://github.com/lcx366/STARQUERY
Author: Chunxiao Li
Author-email: lcx366@126.com
License: MIT
Keywords: StarCatalog
Classifier: Development Status :: 4 - Beta
Classifier: Intended Audience :: Education
Classifier: Intended Audience :: Science/Research
Classifier: Programming Language :: Python :: 3.11
Classifier: Programming Language :: Python :: 3.12
Classifier: Programming Language :: Python :: 3.13
Classifier: License :: OSI Approved :: MIT License
Requires-Python: >=3.10
License-File: LICENSE
Requires-Dist: numpy
Requires-Dist: scipy
Requires-Dist: astropy
Requires-Dist: pandas
Requires-Dist: h5py
Requires-Dist: healpy
Requires-Dist: cartopy
Requires-Dist: wget
Requires-Dist: tqdm
Requires-Dist: natsort
Requires-Dist: duckdb
Dynamic: author
Dynamic: author-email
Dynamic: classifier
Dynamic: description
Dynamic: description-content-type
Dynamic: home-page
Dynamic: keywords
Dynamic: license
Dynamic: license-file
Dynamic: requires-dist
Dynamic: requires-python
Dynamic: summary
